mini_groove-0.1.4.dist-info/METADATA
mini_groove-0.1.4.dist-info/WHEEL
mini_groove/__init__.py
mini_groove/__init__.pyi
mini_groove/py.typed
mini_groove/mini_groove.abi3.so
mini_groove-0.1.4.dist-info/RECORD
